mbdb_parsing/__init__.py
mbdb_parsing/base.py
mbdb_parsing/mst.py
mbdb_parsing-0.2.1.dist-info/LICENSE
mbdb_parsing-0.2.1.dist-info/METADATA
mbdb_parsing-0.2.1.dist-info/WHEEL
mbdb_parsing-0.2.1.dist-info/top_level.txt
mbdb_parsing-0.2.1.dist-info/RECORD
