Metadata-Version: 2.1
Name: mbdb-parsing
Version: 0.2.1
Summary: Extract metadata from raw datafiles instruments within the MBDB
Author-email: MBDB <mbdb@ibt.cas.cz>
Project-URL: Homepage, https://github.com/Molecular-Biophysics-Database/mbdb-parsing
Project-URL: Issues, https://github.com/Molecular-Biophysics-Database/mbdb-parsing/issues
Classifier: Programming Language :: Python :: 3
Classifier: License :: OSI Approved :: MIT License
Classifier: Operating System :: OS Independent
Classifier: Development Status :: 4 - Beta
License-File: LICENSE
Requires-Dist: pandas
Requires-Dist: openpyxl
Requires-Dist: invenio-records-resources
Requires-Dist: oarepo-runtime
Requires-Dist: invenio-search
Requires-Dist: opensearch-dsl
Requires-Dist: invenio-drafts-resources
Provides-Extra: dev
Requires-Dist: black ; extra == 'dev'
Requires-Dist: pytest ; extra == 'dev'
